apathetic_logging/__init__.py
apathetic_logging/constants.py
apathetic_logging/dual_stream_handler.py
apathetic_logging/get_logger.py
apathetic_logging/logger.py
apathetic_logging/logger_namespace.py
apathetic_logging/logging_levels.py
apathetic_logging/logging_root.py
apathetic_logging/logging_std_camel.py
apathetic_logging/logging_utils.py
apathetic_logging/namespace.py
apathetic_logging/py.typed
apathetic_logging/registry.py
apathetic_logging/registry_data.py
apathetic_logging/safe_logging.py
apathetic_logging/tag_formatter.py
apathetic_logging-0.22.0.dist-info/METADATA
apathetic_logging-0.22.0.dist-info/WHEEL
apathetic_logging-0.22.0.dist-info/licenses/LICENSE
apathetic_logging-0.22.0.dist-info/RECORD
