Metadata-Version: 2.4
Name: apathetic-logging
Version: 0.22.0
Summary: Small quality-of-life features on top of stdlib.
License-File: LICENSE
Keywords: library,logging,logger
Author: Apathetic Tools
Requires-Python: >=3.10
Classifier: Development Status :: 3 - Alpha
Classifier: Intended Audience :: Developers
Classifier: Operating System :: OS Independent
Classifier: Programming Language :: Python :: 3
Classifier: Programming Language :: Python :: 3 :: Only
Classifier: Programming Language :: Python :: 3.10
Classifier: Programming Language :: Python :: 3.11
Classifier: Programming Language :: Python :: 3.12
Classifier: Topic :: Software Development :: Libraries :: Python Modules
Classifier: Topic :: System :: Logging
Project-URL: Changelog, https://github.com/apathetic-tools/python-logging/releases
Project-URL: Documentation, https://apathetic-tools.github.io/python-logging/
Project-URL: Homepage, https://github.com/apathetic-tools/python-logging
Project-URL: Issues, https://github.com/apathetic-tools/python-logging/issues
Project-URL: Repository, https://github.com/apathetic-tools/python-logging
